rational_protein_design/__init__.py
rational_protein_design/binder_designer.py
rational_protein_design/neighbor_finder.py
rational_protein_design/pdb_parser.py
rational_protein_design/sequence_extractor.py
src/__init__.py
src/binder_designer.py
src/neighbor_finder.py
src/pdb_parser.py
src/sequence_extractor.py
rational_protein_design-0.1.0.dist-info/LICENSE
rational_protein_design-0.1.0.dist-info/METADATA
rational_protein_design-0.1.0.dist-info/WHEEL
rational_protein_design-0.1.0.dist-info/top_level.txt
rational_protein_design-0.1.0.dist-info/RECORD
