Metadata-Version: 2.1
Name: rational_protein_design
Version: 0.1.0
Summary: A package for rational protein binder design using Biopython
Home-page: https://github.com/rohitium/rational_protein_design
Author: Rohit Satija
Author-email: rohitsatija0092@gmail.com
License: MIT
Classifier: Development Status :: 3 - Alpha
Classifier: Intended Audience :: Science/Research
Classifier: Topic :: Scientific/Engineering :: Bio-Informatics
Classifier: License :: OSI Approved :: MIT License
Classifier: Programming Language :: Python :: 3
Classifier: Programming Language :: Python :: 3.7
Classifier: Programming Language :: Python :: 3.8
Classifier: Programming Language :: Python :: 3.9
Classifier: Operating System :: OS Independent
Requires-Python: >=3.7
License-File: LICENSE
Requires-Dist: biopython>=1.79
Requires-Dist: numpy>=1.21.0
Requires-Dist: setuptools>=49.6.0
